scripts/__init__.py
scripts/aliases.json
scripts/check.py
scripts/gen_models.py
amigo_sdk/__init__.py
amigo_sdk/_retry_utils.py
amigo_sdk/auth.py
amigo_sdk/config.py
amigo_sdk/errors.py
amigo_sdk/http_client.py
amigo_sdk/models.py
amigo_sdk/sdk_client.py
amigo_sdk/generated/model.py
amigo_sdk/resources/conversation.py
amigo_sdk/resources/organization.py
amigo_sdk/resources/service.py
amigo_sdk/resources/user.py
amigo_sdk-0.106.0.dist-info/METADATA
amigo_sdk-0.106.0.dist-info/WHEEL
amigo_sdk-0.106.0.dist-info/entry_points.txt
amigo_sdk-0.106.0.dist-info/licenses/LICENSE
amigo_sdk-0.106.0.dist-info/RECORD
