Metadata-Version: 2.4
Name: amigo_sdk
Version: 0.106.0
Summary: Amigo AI Python SDK
Author: Amigo AI
License-File: LICENSE
Classifier: Programming Language :: Python :: 3
Classifier: Programming Language :: Python :: 3 :: Only
Classifier: Programming Language :: Python :: 3.13
Requires-Python: >=3.13
Requires-Dist: email-validator<3.0,>=2.0
Requires-Dist: httpx<1.0,>=0.25
Requires-Dist: pydantic-settings<3.0,>=2.0
Requires-Dist: pydantic<3.0,>=2.7
Provides-Extra: dev
Requires-Dist: datamodel-code-generator[http]<1.0,>=0.21; extra == 'dev'
Requires-Dist: pytest-asyncio<1.0,>=0.21; extra == 'dev'
Requires-Dist: pytest-cov<6.0,>=4.0; extra == 'dev'
Requires-Dist: pytest-httpx<1.0,>=0.30; extra == 'dev'
Requires-Dist: pytest<9.0,>=7.0; extra == 'dev'
Requires-Dist: python-dotenv<2.0,>=1.0; extra == 'dev'
Requires-Dist: ruff<1.0,>=0.1; extra == 'dev'
